jetio/__init__.py
jetio/auth.py
jetio/config.py
jetio/crud.py
jetio/framework.py
jetio/middleware.py
jetio/openapi.py
jetio/orm.py
jetio/security.py
jetio-1.2.0.dist-info/licenses/LICENSE
jetio-1.2.0.dist-info/METADATA
jetio-1.2.0.dist-info/WHEEL
jetio-1.2.0.dist-info/top_level.txt
jetio-1.2.0.dist-info/RECORD
