Metadata-Version: 2.4
Name: jetio
Version: 1.2.0
Summary: A modern, high-performance Python web framework designed to transform your SQLAlchemy models directly into fully-featured, production-ready REST APIs with minimal code. Built with asyncio, SQLAlchemy, and Pydantic.
Home-page: https://github.com/cehstephen/jetio
Author: Stephen Tete
Author-email: cehstephen@gmail.com
Project-URL: Bug Tracker, https://github.com/cehstephen/jetio/issues
Classifier: Programming Language :: Python :: 3
Classifier: License :: OSI Approved :: BSD License
Classifier: Operating System :: OS Independent
Requires-Python: >=3.8
License-File: LICENSE
Requires-Dist: sqlalchemy
Requires-Dist: pydantic[email]
Requires-Dist: pydantic-settings
Requires-Dist: jinja2
Requires-Dist: uvicorn[standard]
Requires-Dist: starlette
Requires-Dist: python-multipart
Requires-Dist: passlib
Requires-Dist: PyJWT
Requires-Dist: aiosqlite
Provides-Extra: bcrypt
Requires-Dist: passlib[bcrypt]; extra == "bcrypt"
Provides-Extra: test
Requires-Dist: pytest; extra == "test"
Requires-Dist: pytest-asyncio; extra == "test"
Requires-Dist: httpx; extra == "test"
Dynamic: license-file
